surreal_commands/__init__.py
surreal_commands/decorators.py
surreal_commands/cli/CLAUDE.md
surreal_commands/cli/__init__.py
surreal_commands/cli/dashboard.py
surreal_commands/cli/launcher.py
surreal_commands/cli/logs.py
surreal_commands/cli/worker.py
surreal_commands/core/CLAUDE.md
surreal_commands/core/__init__.py
surreal_commands/core/client.py
surreal_commands/core/executor.py
surreal_commands/core/registry.py
surreal_commands/core/retry.py
surreal_commands/core/service.py
surreal_commands/core/types.py
surreal_commands/core/worker.py
surreal_commands/repository/CLAUDE.md
surreal_commands/repository/__init__.py
surreal_commands-1.3.1.dist-info/METADATA
surreal_commands-1.3.1.dist-info/WHEEL
surreal_commands-1.3.1.dist-info/entry_points.txt
surreal_commands-1.3.1.dist-info/licenses/LICENSE
surreal_commands-1.3.1.dist-info/RECORD
