Metadata-Version: 2.4
Name: surreal-commands
Version: 1.3.1
Summary: A distributed task queue system similar to Celery, built with Python, SurrealDB, and LangChain
Project-URL: Homepage, https://github.com/lfnovo/surreal-commands
Project-URL: Documentation, https://github.com/lfnovo/surreal-commands/blob/main/README.md
Project-URL: Repository, https://github.com/lfnovo/surreal-commands
Project-URL: Bug Tracker, https://github.com/lfnovo/surreal-commands/issues
Author: Surreal Commands Contributors
Maintainer: Surreal Commands Contributors
License: MIT
License-File: LICENSE
Keywords: async,celery,distributed,langchain,surrealdb,task-queue
Classifier: Development Status :: 5 - Production/Stable
Classifier: Environment :: Console
Classifier: Framework :: AsyncIO
Classifier: Intended Audience :: Developers
Classifier: License :: OSI Approved :: MIT License
Classifier: Operating System :: OS Independent
Classifier: Programming Language :: Python :: 3
Classifier: Programming Language :: Python :: 3.10
Classifier: Programming Language :: Python :: 3.11
Classifier: Programming Language :: Python :: 3.12
Classifier: Topic :: Internet
Classifier: Topic :: Software Development :: Libraries :: Python Modules
Classifier: Topic :: System :: Distributed Computing
Classifier: Topic :: System :: Networking
Classifier: Typing :: Typed
Requires-Python: >=3.10.6
Requires-Dist: humanize>=4.12.3
Requires-Dist: langchain-core>=0.3.68
Requires-Dist: loguru>=0.7.3
Requires-Dist: pydantic>=2.11.7
Requires-Dist: python-dotenv>=1.1.1
Requires-Dist: rich>=14.0.0
Requires-Dist: surrealdb>=1.0.4
Requires-Dist: tenacity>=9.0.0
Requires-Dist: typer>=0.16.0
Provides-Extra: cli
Requires-Dist: click>=8.0.0; extra == 'cli'
Provides-Extra: dev
Requires-Dist: black>=23.0.0; extra == 'dev'
Requires-Dist: mypy>=1.0.0; extra == 'dev'
Requires-Dist: pytest-asyncio>=0.21.0; extra == 'dev'
Requires-Dist: pytest-cov>=4.0.0; extra == 'dev'
Requires-Dist: pytest-mock>=3.10.0; extra == 'dev'
Requires-Dist: pytest-xdist>=3.0.0; extra == 'dev'
Requires-Dist: pytest>=7.0.0; extra == 'dev'
Requires-Dist: ruff>=0.1.0; extra == 'dev'
Provides-Extra: test
Requires-Dist: coverage>=7.0.0; extra == 'test'
Requires-Dist: pytest-asyncio>=0.21.0; extra == 'test'
Requires-Dist: pytest-cov>=4.0.0; extra == 'test'
Requires-Dist: pytest-mock>=3.10.0; extra == 'test'
Requires-Dist: pytest-xdist>=3.0.0; extra == 'test'
Requires-Dist: pytest>=7.0.0; extra == 'test'
